blueprints/__init__.py
blueprints/__main__.py
blueprints/main.py
auto_blueprints-0.1.1.dist-info/LICENSE.txt
auto_blueprints-0.1.1.dist-info/METADATA
auto_blueprints-0.1.1.dist-info/WHEEL
auto_blueprints-0.1.1.dist-info/entry_points.txt
auto_blueprints-0.1.1.dist-info/top_level.txt
auto_blueprints-0.1.1.dist-info/RECORD
