Metadata-Version: 2.1
Name: auto-blueprints
Version: 0.1.1
Summary: Flask blueprints auto discovery
Author-email: David <c0d3@gpobox.net>
Maintainer-email: David <c0d3@gpobox.net>
License: Copyright © 2024 David <c0d3@gpobox.net>
Project-URL: Homepage, https://github.com/bbc6502/blueprints
Project-URL: Bug Tracker, https://github.com/bbc6502/blueprints/issues
Keywords: flask,blueprints
Classifier: Programming Language :: Python :: 3
Classifier: License :: OSI Approved :: MIT License
Classifier: Operating System :: OS Independent
Classifier: Development Status :: 4 - Beta
Requires-Python: >=3.11
License-File: LICENSE.txt
Requires-Dist: Flask >=3.0.0
Provides-Extra: waitress
Requires-Dist: waitress >=3.0.0 ; extra == 'waitress'
